<?xml version="1.0"?>
<Devices>
	<Device type="custom" id="slackAccount">
		<Name>Slack Workspace</Name>
		<ConfigUI>
        	<SupportURL>https://github.com/FlyingDiver/indigo-slack2/issues</SupportURL>
	        <Field id="app_token" type="textfield" default="">
		        <Label>Slack App Token:</Label>
	        </Field>
            <Field id="app_token_help" type="label" fontSize="mini" alignWithControl="true">
                <Label>Required, starts with "xapp-", see wiki for instructions</Label>
            </Field>
	        <Field id="bot_token" type="textfield" default="">
		        <Label>Slack Bot User Token:</Label>
	        </Field>
            <Field id="bot_token_help" type="label" fontSize="mini" alignWithControl="true">
                <Label>Required, starts with "xoxb-", see wiki for instructions</Label>
            </Field>
		</ConfigUI>
		<States>
			<State id="status">
				<ValueType>String</ValueType>
				<TriggerLabel>Status</TriggerLabel>
				<ControlPageLabel>Status</ControlPageLabel>
			</State>
		</States>
    <UiDisplayStateId>status</UiDisplayStateId>
	</Device>
</Devices>